py_cptcore-0.1.0.dist-info/licenses/LICENSE
pycptcore/__init__.py
pycptcore/_version.py
pycptcore/main.py
py_cptcore-0.1.0.dist-info/METADATA
py_cptcore-0.1.0.dist-info/WHEEL
py_cptcore-0.1.0.dist-info/top_level.txt
py_cptcore-0.1.0.dist-info/RECORD
