Metadata-Version: 2.4
Name: py-cptcore
Version: 0.1.0
Summary: Public python SDK for the CEMS CPTCore web-API.
License: MIT License
Project-URL: repository, https://github.com/cemsbv/py-cptcore
Keywords: API,CPTCore,CEMS,CRUX
Requires-Python: >=3.11
License-File: LICENSE
Requires-Dist: requests<3,>=2.25.1
Requires-Dist: pandas<3,>=2
Requires-Dist: matplotlib<4,>=3
Provides-Extra: test
Requires-Dist: coveralls; extra == "test"
Requires-Dist: pytest; extra == "test"
Provides-Extra: docs
Requires-Dist: Sphinx==8.2.3; extra == "docs"
Requires-Dist: asteroid-sphinx-theme==0.0.3; extra == "docs"
Requires-Dist: ipython==9.1.0; extra == "docs"
Requires-Dist: sphinx-autodoc-typehints==3.1.0; extra == "docs"
Requires-Dist: sphinx_rtd_theme==3.0.2; extra == "docs"
Provides-Extra: lint
Requires-Dist: ansible-lint==25.1.3; extra == "lint"
Requires-Dist: black==25.1.0; extra == "lint"
Requires-Dist: cfn-lint==1.25.1; extra == "lint"
Requires-Dist: cpplint==2.0.0; extra == "lint"
Requires-Dist: flake8==7.1.2; extra == "lint"
Requires-Dist: isort==6.0.0; extra == "lint"
Requires-Dist: mypy==1.15.0; extra == "lint"
Requires-Dist: sqlfluff==3.3.1; extra == "lint"
Requires-Dist: yamllint==1.35.1; extra == "lint"
Requires-Dist: yq==3.4.3; extra == "lint"
Dynamic: license-file
